COPYING
MANIFEST.in
README
health_crypto_view.xml
setup.py
./__init__.py
./health_crypto.py
./health_crypto_view.xml
./tryton.cfg
./doc/index.rst
./locale/ar.po
./locale/de.po
./locale/el.po
./locale/es.po
./locale/fr.po
./locale/it_IT.po
./locale/ja_JP.po
./locale/lo.po
./locale/pt_BR.po
./locale/zh_CN.po
./tests/__init__.py
./tests/test_health_crypto.py
./view/gnuhealth_birth_certificate_form.xml
./view/gnuhealth_death_certificate_form.xml
./view/gnuhealth_patient_evaluation_form.xml
./view/prescription_form.xml
locale/ar.po
locale/de.po
locale/el.po
locale/es.po
locale/fr.po
locale/it_IT.po
locale/ja_JP.po
locale/lo.po
locale/pt_BR.po
locale/zh_CN.po
trytond_health_crypto.egg-info/PKG-INFO
trytond_health_crypto.egg-info/SOURCES.txt
trytond_health_crypto.egg-info/dependency_links.txt
trytond_health_crypto.egg-info/entry_points.txt
trytond_health_crypto.egg-info/not-zip-safe
trytond_health_crypto.egg-info/requires.txt
trytond_health_crypto.egg-info/top_level.txt
view/gnuhealth_birth_certificate_form.xml
view/gnuhealth_death_certificate_form.xml
view/gnuhealth_patient_evaluation_form.xml
view/prescription_form.xml